psi4_step/__init__.py
psi4_step/__main__.py
psi4_step/_version.py
psi4_step/energy.py
psi4_step/energy_parameters.py
psi4_step/energy_step.py
psi4_step/initialization.py
psi4_step/initialization_parameters.py
psi4_step/initialization_step.py
psi4_step/installer.py
psi4_step/optimization.py
psi4_step/optimization_parameters.py
psi4_step/optimization_step.py
psi4_step/optimizer.py
psi4_step/psi4.py
psi4_step/psi4_metadata.py
psi4_step/psi4_parameters.py
psi4_step/psi4_step.py
psi4_step/thermochemistry.py
psi4_step/thermochemistry_parameters.py
psi4_step/thermochemistry_step.py
psi4_step/tk_energy.py
psi4_step/tk_initialization.py
psi4_step/tk_optimization.py
psi4_step/tk_psi4.py
psi4_step/tk_thermochemistry.py
psi4_step/data/MOPAC_PM7_Hessian.flow
psi4_step/data/MOPAC_PM7_SPE.flow
psi4_step/data/MOPAC_PM7_surrogate.flow
psi4_step/data/atom_energies.csv
psi4_step/data/configuration.txt
psi4_step/data/opt_log.out
psi4_step/data/properties.csv
psi4_step/data/psi4.ini
psi4_step/data/references.bib
psi4_step/data/seamm-psi4.yml
psi4_step-2025.3.9.dist-info/AUTHORS.rst
psi4_step-2025.3.9.dist-info/LICENSE
psi4_step-2025.3.9.dist-info/METADATA
psi4_step-2025.3.9.dist-info/WHEEL
psi4_step-2025.3.9.dist-info/entry_points.txt
psi4_step-2025.3.9.dist-info/top_level.txt
psi4_step-2025.3.9.dist-info/zip-safe
psi4_step-2025.3.9.dist-info/RECORD
